AUTHORS.txt
LICENSE-GPL.txt
MANIFEST.in
NOTICE.txt
README.rst
reg_settings.py
setup.py
neo4django/__init__.py
neo4django/benchmarks.py
neo4django/constants.py
neo4django/decorators.py
neo4django/exceptions.py
neo4django/neo4jclient.py
neo4django/rest_utils.py
neo4django/testutils.py
neo4django/utils.py
neo4django/validators.py
neo4django.egg-info/PKG-INFO
neo4django.egg-info/SOURCES.txt
neo4django.egg-info/dependency_links.txt
neo4django.egg-info/requires.txt
neo4django.egg-info/top_level.txt
neo4django/db/__init__.py
neo4django/db/models/__init__.py
neo4django/db/models/base.py
neo4django/db/models/manager.py
neo4django/db/models/properties.py
neo4django/db/models/query.py
neo4django/db/models/relationships.py
neo4django/db/models/script_utils.py
neo4django/gremlin/__init__.py
neo4django/gremlin/library.groovy
neo4django/tests/__init__.py
neo4django/tests/django_tests.py
neo4django/tests/index_tests.py
neo4django/tests/model_tests.py
neo4django/tests/models.py
neo4django/tests/neo4jclient_tests.py
neo4django/tests/nodequeryset_tests.py
neo4django/tests/property_tests.py
neo4django/tests/relationship_tests.py
neo4django/tests/signal_tests.py
neo4django/tests/synchronicity_tests.py
neo4django/tests/test_settings.py