Metadata-Version: 1.0
Name: neo4django
Version: 0.1.7
Summary: A Django/Neo4j ORM layer based on the neo4j.py.
Home-page: http://packages.python.org/neo4django
Author: Matt Luongo
Author-email: mhluongo@gmail.com
License: GPL
Platform: posix
Classifier: Development Status :: 2 - Pre-Alpha
Classifier: License :: OSI Approved :: GNU General Public License (GPL)
Classifier: Operating System :: POSIX
